todo_cli/__init__.py
todo_cli/core.py
todo_cli/main.py
todo_cli/utils.py
todo_cli_x-1.2.0.dist-info/licenses/LICENSE
todo_cli_x-1.2.0.dist-info/METADATA
todo_cli_x-1.2.0.dist-info/WHEEL
todo_cli_x-1.2.0.dist-info/entry_points.txt
todo_cli_x-1.2.0.dist-info/top_level.txt
todo_cli_x-1.2.0.dist-info/RECORD
