Metadata-Version: 2.4
Name: todo-cli-x
Version: 1.2.0
Summary: A simple command-line todo application
Author-email: vidjinnangni <gregory.thoto@gmail.com>
Project-URL: Homepage, https://pypi.org/project/todo-cli-x/
Project-URL: Documentation, https://todocli.vmslab.work/
Project-URL: Repository, https://github.com/vidjinnangni/todo-cli-x
Project-URL: Roadmap, https://vidjinnangni.notion.site/Todo-CLI-Roadmap-207873f9fe5a80f38256eb0b0798e30a
Requires-Python: >=3.11
License-File: LICENSE
Provides-Extra: dev
Requires-Dist: pytest>=8.3.5; extra == "dev"
Requires-Dist: ruff>=0.11.13; extra == "dev"
Dynamic: license-file
